{
  "notes": [
    {
      "id": "bde1",
      "title": "A faire /!\\",
      "content": "- Affichage des messages d'erreurs\n- Theme jour/nuit ? \n- pagination (overflow-y:auto)\n- tags ",
      "date": "2024-04-05T12:40:52.248Z",
      "isPin": true,
      "isCheck": false
    },
    {
      "id": "2204",
      "title": "11111122223333333",
      "content": "1111122222222222222",
      "date": "2024-04-05T10:06:21.015Z",
      "isPin": true,
      "isCheck": false
    },
    {
      "id": "b21f",
      "title": "banane",
      "content": "1111111111111111111111",
      "date": "2024-04-05T10:42:57.552Z",
      "isPin": false,
      "isCheck": true
    },
    {
      "id": "1910",
      "title": "36151",
      "content": "36151",
      "date": "2024-04-05T09:52:48.485Z",
      "isPin": false,
      "isCheck": false
    },
    {
      "id": "b0c7",
      "title": "azerty2",
      "content": "banane",
      "date": "2024-04-05T10:42:50.854Z",
      "isPin": false,
      "isCheck": false
    },
    {
      "id": "cf68",
      "title": "Nouvelle notePined et Checked",
      "content": "",
      "date": "2024-04-05T12:02:58.608Z",
      "isCheck": true,
      "isPin": true
    },
    {
      "id": "abbf",
      "title": "Nouvelle note",
      "content": "test",
      "date": "2024-04-05T12:10:32.049Z"
    }
  ],
  "profile": {
    "name": "John Doe"
  }
}